transliterate/__init__.py
transliterate/base.py
transliterate/conf.py
transliterate/decorators.py
transliterate/defaults.py
transliterate/discover.py
transliterate/exceptions.py
transliterate/helpers.py
transliterate/utils.py
transliterate/contrib/__init__.py
transliterate/contrib/apps/__init__.py
transliterate/contrib/apps/translipsum/__init__.py
transliterate/contrib/apps/translipsum/utils.py
transliterate/contrib/languages/__init__.py
transliterate/contrib/languages/bg/__init__.py
transliterate/contrib/languages/bg/translit_language_pack.py
transliterate/contrib/languages/bg/data/__init__.py
transliterate/contrib/languages/bg/data/default.py
transliterate/contrib/languages/el/__init__.py
transliterate/contrib/languages/el/translit_language_pack.py
transliterate/contrib/languages/el/data/__init__.py
transliterate/contrib/languages/el/data/default.py
transliterate/contrib/languages/he/__init__.py
transliterate/contrib/languages/he/translit_language_pack.py
transliterate/contrib/languages/hi/__init__.py
transliterate/contrib/languages/hi/translit_language_pack.py
transliterate/contrib/languages/hy/__init__.py
transliterate/contrib/languages/hy/translit_language_pack.py
transliterate/contrib/languages/hy/data/__init__.py
transliterate/contrib/languages/hy/data/default.py
transliterate/contrib/languages/ka/__init__.py
transliterate/contrib/languages/ka/translit_language_pack.py
transliterate/contrib/languages/ka/data/__init__.py
transliterate/contrib/languages/ka/data/default.py
transliterate/contrib/languages/l1/__init__.py
transliterate/contrib/languages/l1/translit_language_pack.py
transliterate/contrib/languages/l1/data/__init__.py
transliterate/contrib/languages/l1/data/default.py
transliterate/contrib/languages/mk/__init__.py
transliterate/contrib/languages/mk/translit_language_pack.py
transliterate/contrib/languages/mk/data/__init__.py
transliterate/contrib/languages/mk/data/default.py
transliterate-1.10.1.dist-info/DESCRIPTION.rst
transliterate-1.10.1.dist-info/METADATA
transliterate-1.10.1.dist-info/RECORD
transliterate-1.10.1.dist-info/WHEEL
transliterate-1.10.1.dist-info/metadata.json
transliterate-1.10.1.dist-info/top_level.txt
