Metadata-Version: 1.1
Name: transliterate
Version: 1.10.1
Summary: Bi-directional transliterator for Python
Home-page: https://github.com/barseghyanartur/transliterate
Author: Artur Barseghyan
Author-email: artur.barseghyan@gmail.com
License: GPL 2.0/LGPL 2.1
Keywords: translit,transliteration
Platform: UNKNOWN
Classifier: Programming Language :: Python
Classifier: Programming Language :: Python :: 2.7
Classifier: Programming Language :: Python :: 3
Classifier: Programming Language :: Python :: 3.4
Classifier: Programming Language :: Python :: 3.5
Classifier: Programming Language :: Python :: Implementation :: PyPy
Classifier: Intended Audience :: Developers
Classifier: Operating System :: OS Independent
Classifier: Development Status :: 4 - Beta
Classifier: Natural Language :: Bulgarian
Classifier: Natural Language :: Greek
Classifier: Natural Language :: Macedonian
Classifier: Natural Language :: Russian
Classifier: Natural Language :: Serbian
Classifier: Natural Language :: Ukrainian
